MANIFEST.in
README.rst
requirements.txt
setup.py
datatree/__init__.py
datatree/symbols.py
datatree/tree.py
datatree/utils.py
datatree.egg-info/PKG-INFO
datatree.egg-info/SOURCES.txt
datatree.egg-info/dependency_links.txt
datatree.egg-info/top_level.txt
datatree/render/__init__.py
datatree/render/base.py
datatree/render/dictrender.py
datatree/render/etreerender.py
datatree/render/jsonrender.py
datatree/render/xmlrenderer.py
datatree/render/yamlrender.py
datatree/tests/__init__.py
datatree/tests/test_dictrenderer.py
datatree/tests/test_etreerender.py
datatree/tests/test_jsonrenderer.py
datatree/tests/test_node.py
datatree/tests/test_rendererbase.py
datatree/tests/test_symbol.py
datatree/tests/test_tree.py
datatree/tests/test_xmlrenderer.py
datatree/tests/test_yamlrenderer.py