Metadata-Version: 1.0
Name: datatree
Version: 0.1.8
Summary: DSL for creating structured documents in python.
Home-page: https://github.com/bigjason/datatree
Author: Jason Webb
Author-email: bigjasonwebb@gmail.com
License: Creative Commons Attribution 3.0 Unported License
Platform: UNKNOWN
Classifier: Development Status :: 4 - Beta
Classifier: Topic :: Text Processing :: Markup
Classifier: Topic :: Text Processing :: Markup :: XML
Classifier: Operating System :: OS Independent
Classifier: Intended Audience :: Developers
Classifier: Programming Language :: Python :: 2.6
Classifier: Programming Language :: Python :: 2.7
